pylogram/__init__.py
pylogram/client.py
pylogram/constants.py
pylogram/dispatcher.py
pylogram/emoji.py
pylogram/file_id.py
pylogram/filters.py
pylogram/middleware.py
pylogram/mime_types.py
pylogram/peers.py
pylogram/py.typed
pylogram/raw_parsers.py
pylogram/typevars.py
pylogram/utils.py
pylogram/connection/__init__.py
pylogram/connection/connection.py
pylogram/connection/transport/__init__.py
pylogram/connection/transport/tcp/__init__.py
pylogram/connection/transport/tcp/tcp.py
pylogram/connection/transport/tcp/tcp_abridged.py
pylogram/connection/transport/tcp/tcp_abridged_o.py
pylogram/connection/transport/tcp/tcp_full.py
pylogram/connection/transport/tcp/tcp_intermediate.py
pylogram/connection/transport/tcp/tcp_intermediate_o.py
pylogram/crypto/__init__.py
pylogram/crypto/aes.py
pylogram/crypto/mtproto.py
pylogram/crypto/prime.py
pylogram/crypto/rsa.py
pylogram/enums/__init__.py
pylogram/enums/auto_name.py
pylogram/enums/chat_action.py
pylogram/enums/chat_event_action.py
pylogram/enums/chat_member_status.py
pylogram/enums/chat_members_filter.py
pylogram/enums/chat_type.py
pylogram/enums/message_entity_type.py
pylogram/enums/message_media_type.py
pylogram/enums/message_service_type.py
pylogram/enums/messages_filter.py
pylogram/enums/next_code_type.py
pylogram/enums/parse_mode.py
pylogram/enums/poll_type.py
pylogram/enums/sent_code_type.py
pylogram/enums/user_status.py
pylogram/errors/__init__.py
pylogram/errors/lib_errors.py
pylogram/errors/rpc_error.py
pylogram/handlers/__init__.py
pylogram/handlers/callback_query_handler.py
pylogram/handlers/chat_join_request_handler.py
pylogram/handlers/chat_member_updated_handler.py
pylogram/handlers/chosen_inline_result_handler.py
pylogram/handlers/deleted_messages_handler.py
pylogram/handlers/disconnect_handler.py
pylogram/handlers/edited_message_handler.py
pylogram/handlers/handler.py
pylogram/handlers/inline_query_handler.py
pylogram/handlers/message_handler.py
pylogram/handlers/poll_handler.py
pylogram-0.11.6.dist-info/METADATA
pylogram-0.11.6.dist-info/WHEEL
pylogram-0.11.6.dist-info/entry_points.txt
pylogram-0.11.6.dist-info/licenses/LICENSE.txt
pylogram-0.11.6.dist-info/licenses/NOTICE
pylogram-0.11.6.dist-info/RECORD
