Metadata-Version: 2.4
Name: pylogram
Version: 0.11.6
Summary: Elegant, modern and asynchronous Telegram MTProto API framework in Python for users and bots
Project-URL: Source, https://github.com/pylakey/pylogram
Project-URL: Homepage, https://github.com/pylakey/pylogram
Author-email: Dan <dan@pyrogram.org>, Pylakey <pylakey@protonmail.com>
Maintainer-email: Pylakey <pylakey@protonmail.com>
License-Expression: LGPL-3.0
License-File: LICENSE.txt
License-File: NOTICE
Keywords: api,chat,client,library,messenger,mtproto,python,telegram
Classifier: Development Status :: 5 - Production/Stable
Classifier: Intended Audience :: Developers
Classifier: License :: OSI Approved :: GNU Lesser General Public License v3 (LGPLv3)
Classifier: Natural Language :: English
Classifier: Operating System :: OS Independent
Classifier: Programming Language :: Python
Classifier: Programming Language :: Python :: 3
Classifier: Programming Language :: Python :: 3.10
Classifier: Programming Language :: Python :: 3.11
Classifier: Programming Language :: Python :: 3.12
Classifier: Programming Language :: Python :: Implementation
Classifier: Programming Language :: Python :: Implementation :: CPython
Classifier: Programming Language :: Python :: Implementation :: PyPy
Classifier: Topic :: Communications
Classifier: Topic :: Communications :: Chat
Classifier: Topic :: Internet
Classifier: Topic :: Software Development :: Libraries
Classifier: Topic :: Software Development :: Libraries :: Application Frameworks
Classifier: Topic :: Software Development :: Libraries :: Python Modules
Requires-Python: >=3.10
Requires-Dist: python-socks[asyncio]<2.6.0,>=2.4.4
Requires-Dist: tgcrypto~=1.2.5
